esobrute/__init__.py
esobrute-0.1.data/scripts/esobrute
esobrute-0.1.dist-info/LICENSE
esobrute-0.1.dist-info/METADATA
esobrute-0.1.dist-info/WHEEL
esobrute-0.1.dist-info/top_level.txt
esobrute-0.1.dist-info/RECORD
