Metadata-Version: 2.1
Name: esobrute
Version: 0.1
Summary: An esoteric programming languages brute forcer powered by tio.run
Home-page: https://github.com/tcode2k16/esobrute
Author: Alan Chang
Author-email: tcode2k16@gmail.com
License: MIT
Platform: UNKNOWN
Classifier: License :: OSI Approved :: MIT License
Classifier: Topic :: Security
Classifier: Environment :: Console
Classifier: Operating System :: OS Independent
Classifier: Programming Language :: Python :: 2.7
Classifier: Intended Audience :: Developers
Requires-Python: >=2.7, <3
Requires-Dist: requests (>=2.20.1)
Requires-Dist: termcolor (>=1.1.0)
Requires-Dist: Click (>=7.0)
